{
    "genres": {
        "Action": 0,
        "Sports": 1,
        "Platform": 2,
        "Shooter": 3,
        "Role-playing": 4,
        "Multi": 5,
        "Adventure": 6,
        "Puzzle": 7,
        "Racing": 8,
        "Fighting": 9,
        "Arcade": 10,
        "Classic": 11,
        "Strategy": 12
    },
    "composers": {
        "Takeaki Kunimoto": 0,
        "Koji Kondo": 1,
        "Mendelssohn": 2,
        "Michiharu Hasuya": 3,
        "Kenichi Matsubara": 4,
        "Yuichi Sakakura": 5,
        "Satoko Minami": 6,
        "Tsukasa Masuko": 7,
        "Hirokazu Tanaka": 8,
        "Nobuyuki Shioda": 9,
        "Hideya Nagata": 10,
        "Masaaki Harada": 11,
        "Mieko Ishikawa": 12,
        "Osamu Kasai": 13,
        "Shinji Nakayama": 14,
        "Yuzo Koshiro": 15,
        "Mike Smith": 16,
        "Jun Chikuma": 17,
        "Shunsuke Kikuchi": 18,
        "K. Suzuki": 19,
        "Shigemasa Matsuo": 20,
        "Takashi Tateishi": 21,
        "Junko Ozawa": 22,
        "Harumi Fujita": 23,
        "Shotaro Sasaki": 24,
        "Norio Nakagata": 25,
        "Daisuke Inoue": 26,
        "Hideki Kanazashi": 27,
        "Yukio Kaneoka": 28,
        "Yoshihiro Sakaguchi": 29,
        "Hiroyuki Kawada": 30,
        "Joyful Ide": 31,
        "Masakatsu Maekawa": 32,
        "Osamu Ohta": 33,
        "Hirokazu Ando": 34,
        "Jun Ishikawa": 35,
        "Mikio Saito": 36,
        "Takane Ohkubo": 37,
        "Atsushi Fujio": 38,
        "Hidenori Maezawa": 39,
        "Kazuhiko Uehara": 40,
        "Kinuyo Yamashita": 41,
        "Kiyohiro Sada": 42,
        "Shinya Sakamoto": 43,
        "Satoe Terashima": 44,
        "Tim Follin": 45,
        "Chen Yi": 46,
        "Hiroto Tomro": 47,
        "Yuriko Keino": 48,
        "Brian Johnston": 49,
        "Jonathan Dunn": 50,
        "Tim Wright": 51,
        "Naoki Kodaka": 52,
        "Tamayo Kawamoto": 53,
        "Katsuhiro Hayashi": 54,
        "Martin Galway": 55,
        "Katsuya Ogawa": 56,
        "Hiroyuki Masuno": 57,
        "Shigehiro Takenouchi": 58,
        "Yoshinori Sasaki": 59,
        "Roger Deforest": 60,
        "Mark Harris": 61,
        "Don Koch": 62,
        "Tetsuya Komuro": 63,
        "TM Network": 64,
        "Takashi Utsunomiya": 65,
        "Naoto Kine": 66,
        "Satoshi Kadokura": 67,
        "Kouichi Ishibashi": 68,
        "Yuka Tsujiyoko": 69,
        "Iku Mizutani": 70,
        "Masanori Adachi": 71,
        "Yoshinobu Kasukawa": 72,
        "Hiromi Shibano": 73,
        "Geoff Follin": 74,
        "Yasuko Yamada": 75,
        "Kji Murata": 76,
        "Kazuhiro Nishida": 77,
        "Kikuko Hataya": 78,
        "Toshikazu Tanaka": 79,
        "Yoko Osaka": 80,
        "Hirohiko Takayama": 81,
        "Kazuki Muraoka": 82,
        "Dota Ando": 83,
        "Aran Lee": 84,
        "Nobuyuki Hara": 85,
        "Shinichi Seya": 86,
        "Hiroaki Matsuzawa": 87,
        "Nobuo Yamada": 88,
        "Brad Fuller": 89,
        "David Wise": 90,
        "Hal Canon": 91,
        "Koichi Sugiyama": 92,
        "K. Kawamuki": 93,
        "Shiro Imaoka": 94,
        "Masahiko Ishida": 95,
        "Nobuo Uematsu": 96,
        "Neil Baldwin": 97,
        "Shogo Sakai": 98,
        "Takafumi Miura": 99,
        "Yuji Suzuki": 100,
        "Yusuke Takahama": 101,
        "Seiji Momoi": 102,
        "Antonn Dvok": 103,
        "Toshiyuki Sasagawa": 104,
        "Chisa Ichikawa": 105,
        "Kenji Nishi": 106,
        "Pinch Punch": 107,
        "Yoshinori Ohashi": 108,
        "Soyo Oka": 109,
        "Nobuyuki Ohnogi": 110,
        "Jun Chuma": 111,
        "Yasuhiko Manno": 112,
        "Kazuo Sawa": 113,
        "Rob Hubbard": 114,
        "Kouji Murata": 115,
        "Shunichi Mikame": 116,
        "Yuki Kume": 117,
        "Paul Webb": 118,
        "Miki Higashino": 119,
        "Akito Nakatsuka": 120,
        "Kenji Yamamoto": 121,
        "Eveline Fischer": 122,
        "Hiroshige Tonomura": 123,
        "Noboru Machida": 124,
        "Tohru Nakabayashi": 125,
        "Ikuko Mimori": 126,
        "Manami Matsumae": 127,
        "Isamu Hirano": 128,
        "Georges Bizet": 129,
        "Jacques Offenbach": 130,
        "Isao Mizuguchi": 131,
        "Masahiko Takaki": 132,
        "Noboru Koshinaka": 133,
        "Tatsuya Uemura": 134,
        "Hiroshi Uchiki": 135,
        "Keiji Yamagishi": 136,
        "Johann Strauss II": 137,
        "Pyotr Ilyich Tchaikovsky": 138,
        "Kunio Komatsu": 139,
        "Yoki Shinjyuku": 140,
        "Junichi Masuda": 141,
        "David O'Riva": 142,
        "Naoki Higashio": 143,
        "Yasuhiro Kawakami": 144,
        "Fumio Miyashita": 145,
        "Kenji Yoshida": 146,
        "Akio Ohmori": 147,
        "Keiichi Suzuki": 148,
        "Ritsuo Kamimura": 149,
        "Alex Semenov": 150,
        "Koichi Yamanishi": 151,
        "Hiroshi Kawaguchi": 152,
        "Naohisa Morota": 153,
        "Motoaki Furukawa": 154,
        "Haruki Adachi": 155,
        "Peru": 156,
        "Hiroshi Takeyasu": 157,
        "Kozo Nakamura": 158,
        "Paul Wilkinson": 159,
        "Billy Joel": 160,
        "Richard Armadijo": 161,
        "Hiroshi Suzuki": 162,
        "Nikolai Andreyevich Nikolai Rimsky-Korsakov": 163,
        "Ryuichi Nitta": 164,
        "John Williams": 165,
        "Basil Poledouris": 166,
        "Masaaki Iwasaki": 167,
        "S. Takahagi": 168,
        "M. Ogata": 169,
        "Kaori Nakabai": 170,
        "Rika Shigeno": 171,
        "Shinichi Sakamoto": 172,
        "Tomoya Tomita": 173,
        "June Chikuma": 174,
        "Hiroyuki Iwatsuki": 175,
        "David Whittaker": 176,
        "Mayuko Okamura": 177,
        "Tokuhiko Uwabo": 178,
        "Yuki Iwai": 179,
        "Toshiyuki Honda": 180,
        "Toukichi Setoguchi": 181,
        "Armadillo": 182,
        "Yoshikazu Kawauchi": 183,
        "Yasunori Shiono": 184,
        "Michio Fujisawa": 185,
        "Minae Fujii": 186,
        "Yasuaki Fujita": 187,
        "Alex North": 188,
        "Mr. O": 189,
        "Hiroshi Sakaguchi": 190,
        "Shigeru Tomita": 191,
        "Planet2": 192,
        "Soul Duke": 193,
        "Yukie Morimoto": 194,
        "Hisayoshi Ogura": 195,
        "Jun Funahashi": 196,
        "Yoko Kanno": 197,
        "Sato": 198,
        "Katsuhiro Hatano": 199,
        "Earl Vickers": 200,
        "Gavan Anderson": 201,
        "Tania Smith": 202,
        "Seiichi Fukami": 203,
        "Shinji Tasaka": 204,
        "Martino": 205,
        "Neil Sedaka": 206,
        "Kuni Kawachi": 207,
        "Masamichi Yamazaki": 208,
        "Neil Brennan": 209,
        "Steve Treccase": 210,
        "Nick Scarim": 211,
        "Masatomo Miyamoto": 212,
        "Takeshi Santo": 213,
        "Mark Knight": 214,
        "Howard Drossin": 215,
        "Jun Senoue": 216,
        "Masaru Setsumaru": 217,
        "Masato Nakamura": 218,
        "Masayuki Nagao": 219,
        "Sachio Ogawa": 220,
        "Tatsuyuki Maeda": 221,
        "Tomonori Sawada": 222,
        "Yoshio Imamura": 223,
        "Shokichi Ishihara": 224,
        "Hiroshi Tuda": 225,
        "K. Fujii": 226,
        "Hiroaki koi": 227,
        "Ayako Mori": 228,
        "Kentaro Haneda": 229,
        "Oh Chan": 230,
        "Ed Bogas": 231,
        "Li Meng": 232,
        "Akira Inoue": 233,
        "Michiya Hirasawa": 234,
        "Takaro Nozaki": 235,
        "Yoshihiro Kameoka": 236,
        "Hirofumi Ino": 237,
        "Ken Arnold": 238,
        "Seiji Toda": 239,
        "Thomas Arne": 240,
        "Osamu Narita": 241,
        "Takeru Hikono": 242,
        "Akira Sato": 243,
        "Nobuya Ikuta": 244,
        "Noriko Nishizaka": 245,
        "Konami Kukeiha Club": 246,
        "Ryota Musha": 247,
        "Cameo Matano": 248,
        "Dokuo Umeno": 249,
        "Seiichi Hamada": 250,
        "Norio Hanzawa": 251,
        "Michiru Yamane": 252,
        "Masaharu Iwata": 253,
        "Hiroki Aoyagi": 254,
        "Toshio Kai": 255,
        "Masahiro Yuge": 256,
        "Takahiko Nagaya": 257,
        "Tsugutoshi Goto": 258,
        "Shigeru Fukutake": 259,
        "Haruhisa Udagawa": 260,
        "Hiroaki Suga": 261,
        "Masakazu Yuasa": 262,
        "Oba": 263,
        "Kumi Yamaga": 264,
        "David Bowie": 265,
        "Trevor Jones": 266,
        "Mari Yamaguchi": 267,
        "Ludwig van Beethoven": 268,
        "David Warhol": 269,
        "Steve Hughes": 270,
        "Shinji Hosoe": 271,
        "David Hayes": 272,
        "Robin Beanland": 273,
        "arr. Yho Yng": 274,
        "Hoyt Curtin": 275,
        "Naoto Yagishita": 276,
        "Takami Asano": 277,
        "Tadashi Kimijima": 278,
        "Hidehiro Funauchi": 279,
        "Katsuhiko Suzuki": 280,
        "Kazuyuki Ohnui": 281,
        "Shizuo Aizawa": 282,
        "Shotaro": 283,
        "Mitsuo Yamamoto": 284,
        "Toshiko Tasaki": 285,
        "Yuko Takehara": 286,
        "Tsukasa Tawada": 287,
        "Hibiki Godai": 288,
        "Hironari Tadokoro": 289,
        "Asder Staff": 290
    },
    "release_years": {
        "1988": 53,
        "1984": 9,
        "1989": 44,
        "1991": 29,
        "1987": 65,
        "Unknown": 2,
        "1985": 41,
        "1986": 38,
        "1992": 29,
        "1990": 54,
        "1993": 10,
        "1995": 2,
        "1983": 5,
        "unreleased": 2,
        "199X": 1,
        "2011": 3,
        "1994": 5,
        "????": 1,
        "1997": 1,
        "1998": 1,
        "1996": 1
    }
}